odoo9_addon_sale_proforma_report-9.0.1.0.0.99.dev3-py2.7-nspkg.pth
odoo9_addon_sale_proforma_report-9.0.1.0.0.99.dev3.dist-info/DESCRIPTION.rst
odoo9_addon_sale_proforma_report-9.0.1.0.0.99.dev3.dist-info/METADATA
odoo9_addon_sale_proforma_report-9.0.1.0.0.99.dev3.dist-info/RECORD
odoo9_addon_sale_proforma_report-9.0.1.0.0.99.dev3.dist-info/WHEEL
odoo9_addon_sale_proforma_report-9.0.1.0.0.99.dev3.dist-info/metadata.json
odoo9_addon_sale_proforma_report-9.0.1.0.0.99.dev3.dist-info/namespace_packages.txt
odoo9_addon_sale_proforma_report-9.0.1.0.0.99.dev3.dist-info/top_level.txt
odoo_addons/sale_proforma_report/README.rst
odoo_addons/sale_proforma_report/__init__.py
odoo_addons/sale_proforma_report/__openerp__.py
odoo_addons/sale_proforma_report/i18n/es.po
odoo_addons/sale_proforma_report/i18n/pt_BR.po
odoo_addons/sale_proforma_report/i18n/ro.po
odoo_addons/sale_proforma_report/i18n/sale_proforma_report.pot
odoo_addons/sale_proforma_report/i18n/sl.po
odoo_addons/sale_proforma_report/models/__init__.py
odoo_addons/sale_proforma_report/models/sale_order.py
odoo_addons/sale_proforma_report/static/description/icon.png
odoo_addons/sale_proforma_report/views/report_saleorder.xml
odoo_addons/sale_proforma_report/views/sale_order_view.xml
