Metadata-Version: 2.0
Name: odoo9-addon-sale-proforma-report
Version: 9.0.1.0.0.99.dev3
Summary: Proforma report option in sale orders
Home-page: http://www.odoomrp.com
Author: OdooMRP team,AvanzOSC,Tecnativa,Eficent
Author-email: UNKNOWN
License: UNKNOWN
Platform: UNKNOWN
Classifier: Programming Language :: Python
Classifier: Framework :: Odoo
Requires-Python: ~=2.7
Requires-Dist: odoo (<9.1a,>=9.0a)
